custom_logging/__init__.py
custom_logging/configuration.py
logging_configuration-0.1.0.dist-info/LICENSE
logging_configuration-0.1.0.dist-info/METADATA
logging_configuration-0.1.0.dist-info/WHEEL
logging_configuration-0.1.0.dist-info/top_level.txt
logging_configuration-0.1.0.dist-info/RECORD
